StinglePhotosToolkit/__init__.py
StinglePhotosToolkit/client.py
StinglePhotosToolkit/mnemonic.py
StinglePhotosToolkit/mnemonic_wordlist.py
StinglePhotosToolkit/model.py
stingle_photos_toolkit-0.2.1.dist-info/LICENSE
stingle_photos_toolkit-0.2.1.dist-info/METADATA
stingle_photos_toolkit-0.2.1.dist-info/WHEEL
stingle_photos_toolkit-0.2.1.dist-info/top_level.txt
stingle_photos_toolkit-0.2.1.dist-info/RECORD
