Metadata-Version: 2.2
Name: stingle-photos-toolkit
Version: 0.2.1
Summary: A Python toolkit to interact with Stingle Photos database and data files
Author-email: Alessandro Rinaldi <ale@alerinaldi.it>
Project-URL: Homepage, https://github.com/porech/stingle-photos-toolkit
Project-URL: Issues, https://github.com/porech/stingle-photos-toolkit/issues
Classifier: Programming Language :: Python :: 3
Classifier: License :: OSI Approved :: GNU Affero General Public License v3
Classifier: Operating System :: OS Independent
Requires-Python: >=3.10
License-File: LICENSE
Requires-Dist: bitarray>=3.0.0
Requires-Dist: boto3>=1.35.94
Requires-Dist: libnacl>=2.1.0
Requires-Dist: mysql-connector-python>=9.1.0
Requires-Dist: pynacl>=1.5.0
